patrick_personnal_lib/DB_manipulation.py
patrick_personnal_lib/__init__.py
patrick_personnal_lib/ask_path_save_load.py
patrick_personnal_lib/excel_utils.py
patrick_personnal_lib-0.0.4.dist-info/LICENSE
patrick_personnal_lib-0.0.4.dist-info/METADATA
patrick_personnal_lib-0.0.4.dist-info/WHEEL
patrick_personnal_lib-0.0.4.dist-info/top_level.txt
patrick_personnal_lib-0.0.4.dist-info/RECORD
