Metadata-Version: 2.1
Name: patrick_personnal_lib
Version: 0.0.4
Summary: personnal librairie test
Author-email: Patrick Dionne <pdionne.83@gmail.com>
Project-URL: Homepage, https://github.com/Psychopatd/Patrick_personnal_library
Project-URL: Issues, https://github.com/Psychopatd/Patrick_personnal_library/issues
Classifier: Programming Language :: Python :: 3
Classifier: License :: OSI Approved :: MIT License
Classifier: Operating System :: OS Independent
Requires-Python: >=3.8
License-File: LICENSE
Requires-Dist: openpyxl >=3.1.5
Requires-Dist: requests >=2.32.2
Requires-Dist: tk >=0.1.0
